deciphon/__init__.py
deciphon/catch_validation.py
deciphon/cli.py
deciphon/download.py
deciphon/filetype.py
deciphon/hmmer_press.py
deciphon/queue.py
deciphon/read_sequences.py
deciphon/service_exit.py
deciphon/worker.py
deciphon-1.0.13.dist-info/METADATA
deciphon-1.0.13.dist-info/WHEEL
deciphon-1.0.13.dist-info/entry_points.txt
deciphon-1.0.13.dist-info/licenses/LICENSE
deciphon-1.0.13.dist-info/RECORD
