Metadata-Version: 2.4
Name: deciphon
Version: 1.0.13
Summary: Individually annotate long, error-prone nucleotide sequences into proteins
Author-email: Danilo Horta <horta@ebi.ac.uk>
License-Expression: MIT
License-File: LICENSE
Requires-Python: ~=3.11
Requires-Dist: cffi~=1.17
Requires-Dist: deciphon-core>=1.0.17
Requires-Dist: deciphon-poster>=0.2.4
Requires-Dist: deciphon-schema>=0.2.0
Requires-Dist: deciphon-snap<2,>=1.0.3
Requires-Dist: deciphon-worker>=0.5.4
Requires-Dist: fasta-reader<4,>=3.0.3
Requires-Dist: h3daemon>=2.0.5
Requires-Dist: h3result<2,>=1.0.3
Requires-Dist: hmmer~=3.4
Requires-Dist: ijson~=3.3
Requires-Dist: loguru<1,>=0.7.2
Requires-Dist: more-itertools~=10.5
Requires-Dist: paho-mqtt>=2.1.0
Requires-Dist: pip>=24.3.1
Requires-Dist: psutil<7,>=6.1.0
Requires-Dist: pydantic~=2.9
Requires-Dist: rich~=13.8
Requires-Dist: typer<0.16,>=0.15
